rm3100.py
circuitpython_rm3100-1.0.1.dist-info/LICENSE
circuitpython_rm3100-1.0.1.dist-info/METADATA
circuitpython_rm3100-1.0.1.dist-info/WHEEL
circuitpython_rm3100-1.0.1.dist-info/top_level.txt
circuitpython_rm3100-1.0.1.dist-info/RECORD
