Metadata-Version: 2.1
Name: circuitpython-rm3100
Version: 1.0.1
Summary: Driver for the RM3100 megnetometer by PNI Corp
Author-email: Adafruit Industries <circuitpython@adafruit.com>
License: MIT
Project-URL: Homepage, https://github.com/furbrain/CircuitPython_RM3100
Keywords: adafruit,blinka,circuitpython,micropython,rm3100,RM3100,magnetometer,geomagnetic,compass,sensor
Classifier: Intended Audience :: Developers
Classifier: Topic :: Software Development :: Libraries
Classifier: Topic :: Software Development :: Embedded Systems
Classifier: Topic :: System :: Hardware
Classifier: License :: OSI Approved :: MIT License
Classifier: Programming Language :: Python :: 3
License-File: LICENSE
Requires-Dist: Adafruit-Blinka
Requires-Dist: adafruit-circuitpython-busdevice
Provides-Extra: optional
